{
"meta":{"test_sets":[],"test_metrics":[],"learn_metrics":[{"best_value":"Min","name":"RMSE"}],"launch_mode":"Train","parameters":"","iteration_count":150,"learn_sets":["learn"],"name":"experiment"},
"iterations":[
{"learn":[13.63320812],"iteration":0,"passed_time":0.01656000894,"remaining_time":2.467441333},
{"learn":[12.6712726],"iteration":1,"passed_time":0.02690091009,"remaining_time":1.990667346},
{"learn":[11.77089296],"iteration":2,"passed_time":0.03748881882,"remaining_time":1.836952122},
{"learn":[10.90420325],"iteration":3,"passed_time":0.04859878527,"remaining_time":1.773855662},
{"learn":[10.17977043],"iteration":4,"passed_time":0.05936632452,"remaining_time":1.721623411},
{"learn":[9.609912652],"iteration":5,"passed_time":0.07095205559,"remaining_time":1.702849334},
{"learn":[9.008113969],"iteration":6,"passed_time":0.08150142147,"remaining_time":1.66495761},
{"learn":[8.47635499],"iteration":7,"passed_time":0.0924642584,"remaining_time":1.641240587},
{"learn":[7.950207358],"iteration":8,"passed_time":0.1035728081,"remaining_time":1.622640661},
{"learn":[7.518577955],"iteration":9,"passed_time":0.1147089004,"remaining_time":1.605924605},
{"learn":[7.149582601],"iteration":10,"passed_time":0.1252801003,"remaining_time":1.583084903},
{"learn":[6.809088498],"iteration":11,"passed_time":0.1357179627,"remaining_time":1.560756571},
{"learn":[6.459924612],"iteration":12,"passed_time":0.1464707515,"remaining_time":1.543576381},
{"learn":[6.157200481],"iteration":13,"passed_time":0.1574440888,"remaining_time":1.529456862},
{"learn":[5.88130418],"iteration":14,"passed_time":0.1677174045,"remaining_time":1.509456641},
{"learn":[5.642106329],"iteration":15,"passed_time":0.1793907633,"remaining_time":1.502397642},
{"learn":[5.402149224],"iteration":16,"passed_time":0.1901718446,"remaining_time":1.48781502},
{"learn":[5.208188344],"iteration":17,"passed_time":0.2008903824,"remaining_time":1.473196137},
{"learn":[4.986067876],"iteration":18,"passed_time":0.2116116285,"remaining_time":1.459006491},
{"learn":[4.821794196],"iteration":19,"passed_time":0.2228763497,"remaining_time":1.448696273},
{"learn":[4.648107154],"iteration":20,"passed_time":0.2337812682,"remaining_time":1.436084933},
{"learn":[4.471981633],"iteration":21,"passed_time":0.245521504,"remaining_time":1.428488751},
{"learn":[4.319519305],"iteration":22,"passed_time":0.2562930017,"remaining_time":1.415183097},
{"learn":[4.209456917],"iteration":23,"passed_time":0.2666814043,"remaining_time":1.400077373},
{"learn":[4.10134542],"iteration":24,"passed_time":0.2768521752,"remaining_time":1.384260876},
{"learn":[4.011902403],"iteration":25,"passed_time":0.2875755881,"remaining_time":1.371514343},
{"learn":[3.936627249],"iteration":26,"passed_time":0.2982893341,"remaining_time":1.358873633},
{"learn":[3.843361204],"iteration":27,"passed_time":0.3087922402,"remaining_time":1.345451904},
{"learn":[3.742660521],"iteration":28,"passed_time":0.3194322339,"remaining_time":1.332803459},
{"learn":[3.638050683],"iteration":29,"passed_time":0.3301592719,"remaining_time":1.320637088},
{"learn":[3.577257824],"iteration":30,"passed_time":0.3408189328,"remaining_time":1.308304936},
{"learn":[3.515111769],"iteration":31,"passed_time":0.3510761647,"remaining_time":1.294593357},
{"learn":[3.450760478],"iteration":32,"passed_time":0.3611065563,"remaining_time":1.280286882},
{"learn":[3.364971621],"iteration":33,"passed_time":0.3712527848,"remaining_time":1.266627148},
{"learn":[3.287443354],"iteration":34,"passed_time":0.3823197499,"remaining_time":1.256193464},
{"learn":[3.234745128],"iteration":35,"passed_time":0.3934185077,"remaining_time":1.245825274},
{"learn":[3.165063391],"iteration":36,"passed_time":0.4034384823,"remaining_time":1.232122933},
{"learn":[3.113127738],"iteration":37,"passed_time":0.4136829638,"remaining_time":1.219276104},
{"learn":[3.064840923],"iteration":38,"passed_time":0.4241005757,"remaining_time":1.207055485},
{"learn":[3.022498543],"iteration":39,"passed_time":0.4342672631,"remaining_time":1.194234974},
{"learn":[2.946344679],"iteration":40,"passed_time":0.4445267034,"remaining_time":1.181790504},
{"learn":[2.920276597],"iteration":41,"passed_time":0.454416174,"remaining_time":1.168498733},
{"learn":[2.88041621],"iteration":42,"passed_time":0.4644630661,"remaining_time":1.155756932},
{"learn":[2.822326857],"iteration":43,"passed_time":0.4748648858,"remaining_time":1.143992679},
{"learn":[2.788034278],"iteration":44,"passed_time":0.4850481988,"remaining_time":1.131779131},
{"learn":[2.740531756],"iteration":45,"passed_time":0.4952742631,"remaining_time":1.119750508},
{"learn":[2.700665568],"iteration":46,"passed_time":0.5053198218,"remaining_time":1.107403014},
{"learn":[2.670977176],"iteration":47,"passed_time":0.5156608896,"remaining_time":1.09577939},
{"learn":[2.615000347],"iteration":48,"passed_time":0.5258799537,"remaining_time":1.083956639},
{"learn":[2.539686013],"iteration":49,"passed_time":0.5366574933,"remaining_time":1.073314987},
{"learn":[2.491305528],"iteration":50,"passed_time":0.54647617,"remaining_time":1.060806683},
{"learn":[2.447723634],"iteration":51,"passed_time":0.5565897308,"remaining_time":1.04895757},
{"learn":[2.421507946],"iteration":52,"passed_time":0.566585413,"remaining_time":1.036958209},
{"learn":[2.366209733],"iteration":53,"passed_time":0.5769969414,"remaining_time":1.02577234},
{"learn":[2.311264183],"iteration":54,"passed_time":0.5872509648,"remaining_time":1.014342576},
{"learn":[2.282157927],"iteration":55,"passed_time":0.5971175181,"remaining_time":1.002304405},
{"learn":[2.229580606],"iteration":56,"passed_time":0.6071609517,"remaining_time":0.9906310265},
{"learn":[2.19984955],"iteration":57,"passed_time":0.6172642622,"remaining_time":0.9791088297},
{"learn":[2.176967571],"iteration":58,"passed_time":0.6274766594,"remaining_time":0.9678029832},
{"learn":[2.144931107],"iteration":59,"passed_time":0.6376826814,"remaining_time":0.9565240221},
{"learn":[2.113679667],"iteration":60,"passed_time":0.6482971743,"remaining_time":0.9458762051},
{"learn":[2.086294551],"iteration":61,"passed_time":0.6583909012,"remaining_time":0.9344903114},
{"learn":[2.039952026],"iteration":62,"passed_time":0.6689838934,"remaining_time":0.9238349004},
{"learn":[1.983112234],"iteration":63,"passed_time":0.6791827902,"remaining_time":0.9126518743},
{"learn":[1.933212714],"iteration":64,"passed_time":0.6894316885,"remaining_time":0.9015645157},
{"learn":[1.889683093],"iteration":65,"passed_time":0.6995138734,"remaining_time":0.8902903843},
{"learn":[1.863473917],"iteration":66,"passed_time":0.7097315624,"remaining_time":0.8792196967},
{"learn":[1.82315443],"iteration":67,"passed_time":0.7200314206,"remaining_time":0.8682731837},
{"learn":[1.794668063],"iteration":68,"passed_time":0.7308095852,"remaining_time":0.8579069044},
{"learn":[1.762145489],"iteration":69,"passed_time":0.7411554448,"remaining_time":0.8470347941},
{"learn":[1.734588915],"iteration":70,"passed_time":0.7517622291,"remaining_time":0.8364678324},
{"learn":[1.700883529],"iteration":71,"passed_time":0.7617382024,"remaining_time":0.8252163859},
{"learn":[1.657397891],"iteration":72,"passed_time":0.7720765618,"remaining_time":0.8143821268},
{"learn":[1.631947901],"iteration":73,"passed_time":0.7825354666,"remaining_time":0.8036850738},
{"learn":[1.609778952],"iteration":74,"passed_time":0.7930594983,"remaining_time":0.7930594983},
{"learn":[1.593700783],"iteration":75,"passed_time":0.8033409393,"remaining_time":0.7822003883},
{"learn":[1.575727181],"iteration":76,"passed_time":0.8133267879,"remaining_time":0.7710760457},
{"learn":[1.537520583],"iteration":77,"passed_time":0.8234232648,"remaining_time":0.7600830137},
{"learn":[1.51378146],"iteration":78,"passed_time":0.8333659871,"remaining_time":0.7489744947},
{"learn":[1.497191342],"iteration":79,"passed_time":0.8434521304,"remaining_time":0.7380206141},
{"learn":[1.481875299],"iteration":80,"passed_time":0.8536361101,"remaining_time":0.7271715012},
{"learn":[1.451515217],"iteration":81,"passed_time":0.8637254618,"remaining_time":0.7162601391},
{"learn":[1.44234856],"iteration":82,"passed_time":0.8745199602,"remaining_time":0.7059377992},
{"learn":[1.414780981],"iteration":83,"passed_time":0.8843208031,"remaining_time":0.6948234881},
{"learn":[1.387876319],"iteration":84,"passed_time":0.8946038275,"remaining_time":0.6841088092},
{"learn":[1.358731116],"iteration":85,"passed_time":0.9057033769,"remaining_time":0.6740118154},
{"learn":[1.341537795],"iteration":86,"passed_time":0.91583598,"remaining_time":0.6631915717},
{"learn":[1.318147416],"iteration":87,"passed_time":0.9265095164,"remaining_time":0.6527680683},
{"learn":[1.297813761],"iteration":88,"passed_time":0.9366079517,"remaining_time":0.6419447759},
{"learn":[1.289969125],"iteration":89,"passed_time":0.9467853895,"remaining_time":0.6311902597},
{"learn":[1.264985603],"iteration":90,"passed_time":0.9573907988,"remaining_time":0.6207259025},
{"learn":[1.239253302],"iteration":91,"passed_time":0.9688954857,"remaining_time":0.6108254149},
{"learn":[1.229347962],"iteration":92,"passed_time":0.9789107935,"remaining_time":0.5999775831},
{"learn":[1.221957873],"iteration":93,"passed_time":0.9889316015,"remaining_time":0.5891507413},
{"learn":[1.20887261],"iteration":94,"passed_time":0.9992806695,"remaining_time":0.5785309139},
{"learn":[1.198480395],"iteration":95,"passed_time":1.009650447,"remaining_time":0.5679283762},
{"learn":[1.188823924],"iteration":96,"passed_time":1.020120435,"remaining_time":0.5573853923},
{"learn":[1.176694773],"iteration":97,"passed_time":1.030388542,"remaining_time":0.5467367775},
{"learn":[1.157181646],"iteration":98,"passed_time":1.040593356,"remaining_time":0.5360632439},
{"learn":[1.145966691],"iteration":99,"passed_time":1.051098262,"remaining_time":0.525549131},
{"learn":[1.140843886],"iteration":100,"passed_time":1.061221365,"remaining_time":0.5148499691},
{"learn":[1.128863976],"iteration":101,"passed_time":1.071630226,"remaining_time":0.5042965771},
{"learn":[1.116882286],"iteration":102,"passed_time":1.082129341,"remaining_time":0.4937871749},
{"learn":[1.107027508],"iteration":103,"passed_time":1.09240274,"remaining_time":0.4831781349},
{"learn":[1.093427505],"iteration":104,"passed_time":1.102711432,"remaining_time":0.4725906136},
{"learn":[1.069957812],"iteration":105,"passed_time":1.113432761,"remaining_time":0.4621796367},
{"learn":[1.063994075],"iteration":106,"passed_time":1.124317387,"remaining_time":0.4518284828},
{"learn":[1.054217758],"iteration":107,"passed_time":1.134802376,"remaining_time":0.4413120352},
{"learn":[1.040273668],"iteration":108,"passed_time":1.145296199,"remaining_time":0.4307994876},
{"learn":[1.034678958],"iteration":109,"passed_time":1.156068863,"remaining_time":0.4203886775},
{"learn":[1.019137889],"iteration":110,"passed_time":1.166585978,"remaining_time":0.4098815598},
{"learn":[1.007767872],"iteration":111,"passed_time":1.176920087,"remaining_time":0.3993121725},
{"learn":[0.9998845024],"iteration":112,"passed_time":1.187006689,"remaining_time":0.388665907},
{"learn":[0.9943925657],"iteration":113,"passed_time":1.1976556,"remaining_time":0.3782070314},
{"learn":[0.986772946],"iteration":114,"passed_time":1.20774641,"remaining_time":0.3675749943},
{"learn":[0.9831163367],"iteration":115,"passed_time":1.217971266,"remaining_time":0.3569915778},
{"learn":[0.969139192],"iteration":116,"passed_time":1.228883351,"remaining_time":0.3466081246},
{"learn":[0.961348715],"iteration":117,"passed_time":1.23877853,"remaining_time":0.3359399404},
{"learn":[0.9543851494],"iteration":118,"passed_time":1.249218309,"remaining_time":0.3254266184},
{"learn":[0.9391346887],"iteration":119,"passed_time":1.267277614,"remaining_time":0.3168194036},
{"learn":[0.9157366323],"iteration":120,"passed_time":1.281964274,"remaining_time":0.3072476359},
{"learn":[0.9118572945],"iteration":121,"passed_time":1.294947298,"remaining_time":0.2972010192},
{"learn":[0.8977797684],"iteration":122,"passed_time":1.305180237,"remaining_time":0.286502979},
{"learn":[0.889944752],"iteration":123,"passed_time":1.316197159,"remaining_time":0.2759768237},
{"learn":[0.8821481757],"iteration":124,"passed_time":1.326489726,"remaining_time":0.2652979451},
{"learn":[0.8702501467],"iteration":125,"passed_time":1.336348904,"remaining_time":0.2545426483},
{"learn":[0.8667681248],"iteration":126,"passed_time":1.346510174,"remaining_time":0.2438561733},
{"learn":[0.8590307808],"iteration":127,"passed_time":1.356536316,"remaining_time":0.2331546793},
{"learn":[0.8532584151],"iteration":128,"passed_time":1.367076223,"remaining_time":0.2225472921},
{"learn":[0.845025921],"iteration":129,"passed_time":1.377360581,"remaining_time":0.2119016278},
{"learn":[0.8348368147],"iteration":130,"passed_time":1.388099369,"remaining_time":0.2013273894},
{"learn":[0.8211685489],"iteration":131,"passed_time":1.398083593,"remaining_time":0.1906477626},
{"learn":[0.8106461969],"iteration":132,"passed_time":1.408506205,"remaining_time":0.1800346277},
{"learn":[0.7998091819],"iteration":133,"passed_time":1.418736477,"remaining_time":0.1694013704},
{"learn":[0.7899073721],"iteration":134,"passed_time":1.430144161,"remaining_time":0.1589049068},
{"learn":[0.7761092095],"iteration":135,"passed_time":1.44057369,"remaining_time":0.1482943505},
{"learn":[0.7698094588],"iteration":136,"passed_time":1.450937175,"remaining_time":0.1376801699},
{"learn":[0.7635274426],"iteration":137,"passed_time":1.461495375,"remaining_time":0.1270865543},
{"learn":[0.7578196],"iteration":138,"passed_time":1.472083242,"remaining_time":0.1164957961},
{"learn":[0.7514486689],"iteration":139,"passed_time":1.482371475,"remaining_time":0.1058836768},
{"learn":[0.7431336347],"iteration":140,"passed_time":1.492742085,"remaining_time":0.09528140969},
{"learn":[0.7342899436],"iteration":141,"passed_time":1.503452831,"remaining_time":0.08470156795},
{"learn":[0.7311388945],"iteration":142,"passed_time":1.514230162,"remaining_time":0.0741231548},
{"learn":[0.7201717027],"iteration":143,"passed_time":1.524728485,"remaining_time":0.06353035354},
{"learn":[0.7142973209],"iteration":144,"passed_time":1.535199765,"remaining_time":0.05293792293},
{"learn":[0.7077786125],"iteration":145,"passed_time":1.545296367,"remaining_time":0.04233688677},
{"learn":[0.6988689777],"iteration":146,"passed_time":1.550072055,"remaining_time":0.03163412358},
{"learn":[0.6945069472],"iteration":147,"passed_time":1.560646589,"remaining_time":0.02108981877},
{"learn":[0.6886841145],"iteration":148,"passed_time":1.571289749,"remaining_time":0.01054556879},
{"learn":[0.6826058535],"iteration":149,"passed_time":1.582285087,"remaining_time":0}
]}